{
"categories": [
    {
"name": "Music and Musical Instruments",      
      "slug": "",
      "description": "",
      "meta": "",
    "order": 176983,
      "child":[
       


 {
   "order": 176983,
   "name": "Music > Cassettes"
 },
 {
   "order": 176984,
   "name": "Music > CDs"
 },
 {
   "order": 176985,
   "name": "Music > Records"
 },
 {
   "order": 618,
   "name": "Music > Other Formats"
 },
 {
   "order": 52473,
   "name": "Music > Storage & Media Accessories"
 },
 {
   "order": 46497,
   "name": "Music > Wholesale Lots > CDs"
 },
 {
   "order": 46501,
   "name": "Music > Wholesale Lots > Records"
 },
 {
   "order": 31610,
   "name": "Music > Wholesale Lots > Cassettes"
 },
 {
   "order": 45104,
   "name": "Music > Wholesale Lots > Other Wholesale Music"
 },
 {
   "order": 101554,
   "name": "Musical Instruments & Gear > Brass > Alto Horns"
 },
 {
   "order": 179014,
   "name": "Musical Instruments & Gear > Brass > Baritones"
 },
 {
   "order": 75557,
   "name": "Musical Instruments & Gear > Brass > Bugles"
 },
 {
   "order": 41396,
   "name": "Musical Instruments & Gear > Brass > Cornets"
 },
 {
   "order": 159943,
   "name": "Musical Instruments & Gear > Brass > Euphoniums"
 },
 {
   "order": 64374,
   "name": "Musical Instruments & Gear > Brass > Flugelhorns"
 },
 {
   "order": 16215,
   "name": "Musical Instruments & Gear > Brass > French Horns"
 },
 {
   "order": 159945,
   "name": "Musical Instruments & Gear > Brass > Mellophones"
 },
 {
   "order": 159944,
   "name": "Musical Instruments & Gear > Brass > Sousaphones"
 },
 {
   "order": 16216,
   "name": "Musical Instruments & Gear > Brass > Trombones"
 },
 {
   "order": 16214,
   "name": "Musical Instruments & Gear > Brass > Trumpets"
 },
 {
   "order": 179015,
   "name": "Musical Instruments & Gear > Brass > Tubas"
 },
 {
   "order": 182139,
   "name": "Musical Instruments & Gear > Brass > Parts & Accessories > Bags & Cases"
 },
 {
   "order": 182140,
   "name": "Musical Instruments & Gear > Brass > Parts & Accessories > Care & Cleaning"
 },
 {
   "order": 182141,
   "name": "Musical Instruments & Gear > Brass > Parts & Accessories > Mouthpieces"
 },
 {
   "order": 182142,
   "name": "Musical Instruments & Gear > Brass > Parts & Accessories > Mutes"
 },
 {
   "order": 182143,
   "name": "Musical Instruments & Gear > Brass > Parts & Accessories > Practice Aids"
 },
 {
   "order": 182144,
   "name": "Musical Instruments & Gear > Brass > Parts & Accessories > Stands"
 },
 {
   "order": 182145,
   "name": "Musical Instruments & Gear > Brass > Parts & Accessories > Straps"
 },
 {
   "order": 182146,
   "name": "Musical Instruments & Gear > Brass > Parts & Accessories > Other Accessories"
 },
 {
   "order": 620,
   "name": "Musical Instruments & Gear > Brass > Other Brass Instruments"
 },
 {
   "order": 69962,
   "name": "Musical Instruments & Gear > DJ Equipment > Amplifiers"
 },
 {
   "order": 69963,
   "name": "Musical Instruments & Gear > DJ Equipment > Cables, Leads & Connectors"
 },
 {
   "order": 69965,
   "name": "Musical Instruments & Gear > DJ Equipment > Cases, Racks & Bags"
 },
 {
   "order": 182110,
   "name": "Musical Instruments & Gear > DJ Equipment > Digital Vinyl Systems (DVS)"
 },
 {
   "order": 14985,
   "name": "Musical Instruments & Gear > DJ Equipment > DJ & Monitoring Headphones"
 },
 {
   "order": 91384,
   "name": "Musical Instruments & Gear > DJ Equipment > DJ CD/MP3 Players"
 },
 {
   "order": 182111,
   "name": "Musical Instruments & Gear > DJ Equipment > DJ Controllers"
 },
 {
   "order": 157158,
   "name": "Musical Instruments & Gear > DJ Equipment > DJ Equipment Packages"
 },
 {
   "order": 19699,
   "name": "Musical Instruments & Gear > DJ Equipment > DJ Mixers"
 },
 {
   "order": 48460,
   "name": "Musical Instruments & Gear > DJ Equipment > DJ Turntables"
 },
 {
   "order": 157161,
   "name": "Musical Instruments & Gear > DJ Equipment > DJ Turntable Parts & Accs"
 },
 {
   "order": 19656,
   "name": "Musical Instruments & Gear > DJ Equipment > Microphones"
 },
 {
   "order": 69967,
   "name": "Musical Instruments & Gear > DJ Equipment > Speakers & Monitors"
 },
 {
   "order": 175833,
   "name": "Musical Instruments & Gear > DJ Equipment > Stands & Supports"
 },
 {
   "order": 163862,
   "name": "Musical Instruments & Gear > DJ Equipment > Other DJ Equipment"
 },
 {
   "order": 33021,
   "name": "Musical Instruments & Gear > Guitars & Basses > Acoustic Guitars"
 },
 {
   "order": 22966,
   "name": "Musical Instruments & Gear > Guitars & Basses > Acoustic Electric Guitars"
 },
 {
   "order": 4713,
   "name": "Musical Instruments & Gear > Guitars & Basses > Bass Guitars"
 },
 {
   "order": 47066,
   "name": "Musical Instruments & Gear > Guitars & Basses > Beginner Packages > Acoustic Guitar"
 },
 {
   "order": 64398,
   "name": "Musical Instruments & Gear > Guitars & Basses > Beginner Packages > Bass Guitar"
 },
 {
   "order": 47074,
   "name": "Musical Instruments & Gear > Guitars & Basses > Beginner Packages > Electric Guitar"
 },
 {
   "order": 181221,
   "name": "Musical Instruments & Gear > Guitars & Basses > Cigar Box Guitars"
 },
 {
   "order": 119544,
   "name": "Musical Instruments & Gear > Guitars & Basses > Classical Guitars"
 },
 {
   "order": 38072,
   "name": "Musical Instruments & Gear > Guitars & Basses > Guitar Amplifiers"
 },
 {
   "order": 47067,
   "name": "Musical Instruments & Gear > Guitars & Basses > Guitar Builder/Luthier Supply"
 },
 {
   "order": 33034,
   "name": "Musical Instruments & Gear > Guitars & Basses > Electric Guitars"
 },
 {
   "order": 181220,
   "name": "Musical Instruments & Gear > Guitars & Basses > Lap & Pedal Steel Guitars"
 },
 {
   "order": 181219,
   "name": "Musical Instruments & Gear > Guitars & Basses > Resonator"
 },
 {
   "order": 159948,
   "name": "Musical Instruments & Gear > Guitars & Basses > Travel Guitars"
 },
 {
   "order": 47075,
   "name": "Musical Instruments & Gear > Guitars & Basses > Parts & Accessories > Cables"
 },
 {
   "order": 33050,
   "name": "Musical Instruments & Gear > Guitars & Basses > Parts & Accessories > Capos"
 },
 {
   "order": 41408,
   "name": "Musical Instruments & Gear > Guitars & Basses > Parts & Accessories > Cases"
 },
 {
   "order": 41411,
   "name": "Musical Instruments & Gear > Guitars & Basses > Parts & Accessories > Effects Pedals > Bass"
 },
 {
   "order": 41412,
   "name": "Musical Instruments & Gear > Guitars & Basses > Parts & Accessories > Effects Pedals > Boards & Cases"
 },
 {
   "order": 41413,
   "name": "Musical Instruments & Gear > Guitars & Basses > Parts & Accessories > Effects Pedals > Chorus"
 },
 {
   "order": 41414,
   "name": "Musical Instruments & Gear > Guitars & Basses > Parts & Accessories > Effects Pedals > Compressors & Sustainers"
 },
 {
   "order": 159952,
   "name": "Musical Instruments & Gear > Guitars & Basses > Parts & Accessories > Effects Pedals > Custom"
 },
 {
   "order": 41415,
   "name": "Musical Instruments & Gear > Guitars & Basses > Parts & Accessories > Effects Pedals > Delay, Echo & Reverb"
 },
 {
   "order": 41416,
   "name": "Musical Instruments & Gear > Guitars & Basses > Parts & Accessories > Effects Pedals > Distortion & Overdrive"
 },
 {
   "order": 101973,
   "name": "Musical Instruments & Gear > Guitars & Basses > Parts & Accessories > Effects Pedals > Filter & Modulation"
 },
 {
   "order": 41417,
   "name": "Musical Instruments & Gear > Guitars & Basses > Parts & Accessories > Effects Pedals > Flangers"
 },
 {
   "order": 41418,
   "name": "Musical Instruments & Gear > Guitars & Basses > Parts & Accessories > Effects Pedals > Fuzz"
 },
 {
   "order": 101974,
   "name": "Musical Instruments & Gear > Guitars & Basses > Parts & Accessories > Effects Pedals > Loopers & Samplers"
 },
 {
   "order": 41419,
   "name": "Musical Instruments & Gear > Guitars & Basses > Parts & Accessories > Effects Pedals > Multi-Effects"
 },
 {
   "order": 41420,
   "name": "Musical Instruments & Gear > Guitars & Basses > Parts & Accessories > Effects Pedals > Phasers & Shifters"
 },
 {
   "order": 101975,
   "name": "Musical Instruments & Gear > Guitars & Basses > Parts & Accessories > Effects Pedals > Power Supplies"
 },
 {
   "order": 41421,
   "name": "Musical Instruments & Gear > Guitars & Basses > Parts & Accessories > Effects Pedals > Processors"
 },
 {
   "order": 41422,
   "name": "Musical Instruments & Gear > Guitars & Basses > Parts & Accessories > Effects Pedals > Wah & Volume"
 },
 {
   "order": 22669,
   "name": "Musical Instruments & Gear > Guitars & Basses > Parts & Accessories > Effects Pedals > Other Guitar Effects Pedals"
 },
 {
   "order": 148640,
   "name": "Musical Instruments & Gear > Guitars & Basses > Parts & Accessories > Footrests"
 },
 {
   "order": 183389,
   "name": "Musical Instruments & Gear > Guitars & Basses > Parts & Accessories > Amplifier Parts & Accessories"
 },
 {
   "order": 41406,
   "name": "Musical Instruments & Gear > Guitars & Basses > Parts & Accessories > Guitar Parts > Bodies"
 },
 {
   "order": 41407,
   "name": "Musical Instruments & Gear > Guitars & Basses > Parts & Accessories > Guitar Parts > Bridges"
 },
 {
   "order": 170605,
   "name": "Musical Instruments & Gear > Guitars & Basses > Parts & Accessories > Guitar Parts > Capacitors"
 },
 {
   "order": 47076,
   "name": "Musical Instruments & Gear > Guitars & Basses > Parts & Accessories > Guitar Parts > Knobs, Jacks, Switches"
 },
 {
   "order": 41423,
   "name": "Musical Instruments & Gear > Guitars & Basses > Parts & Accessories > Guitar Parts > Necks"
 },
 {
   "order": 101976,
   "name": "Musical Instruments & Gear > Guitars & Basses > Parts & Accessories > Guitar Parts > Nuts"
 },
 {
   "order": 41424,
   "name": "Musical Instruments & Gear > Guitars & Basses > Parts & Accessories > Guitar Parts > Pickguards"
 },
 {
   "order": 22670,
   "name": "Musical Instruments & Gear > Guitars & Basses > Parts & Accessories > Guitar Parts > Pickups"
 },
 {
   "order": 85856,
   "name": "Musical Instruments & Gear > Guitars & Basses > Parts & Accessories > Guitar Parts > Plates"
 },
 {
   "order": 101977,
   "name": "Musical Instruments & Gear > Guitars & Basses > Parts & Accessories > Guitar Parts > Saddles"
 },
 {
   "order": 148648,
   "name": "Musical Instruments & Gear > Guitars & Basses > Parts & Accessories > Guitar Parts > Tremolos"
 },
 {
   "order": 41434,
   "name": "Musical Instruments & Gear > Guitars & Basses > Parts & Accessories > Guitar Parts > Tuning Pegs"
 },
 {
   "order": 46678,
   "name": "Musical Instruments & Gear > Guitars & Basses > Parts & Accessories > Guitar Parts > Other Guitar Parts"
 },
 {
   "order": 46682,
   "name": "Musical Instruments & Gear > Guitars & Basses > Parts & Accessories > Picks"
 },
 {
   "order": 46680,
   "name": "Musical Instruments & Gear > Guitars & Basses > Parts & Accessories > Polishes & Cleaners"
 },
 {
   "order": 85857,
   "name": "Musical Instruments & Gear > Guitars & Basses > Parts & Accessories > Slides"
 },
 {
   "order": 22671,
   "name": "Musical Instruments & Gear > Guitars & Basses > Parts & Accessories > Stands & Hangers"
 },
 {
   "order": 46677,
   "name": "Musical Instruments & Gear > Guitars & Basses > Parts & Accessories > Straps"
 },
 {
   "order": 41431,
   "name": "Musical Instruments & Gear > Guitars & Basses > Parts & Accessories > Strings"
 },
 {
   "order": 22672,
   "name": "Musical Instruments & Gear > Guitars & Basses > Parts & Accessories > Tuners"
 },
 {
   "order": 7266,
   "name": "Musical Instruments & Gear > Guitars & Basses > Parts & Accessories > Other Guitar Parts & Accs"
 },
 {
   "order": 621,
   "name": "Musical Instruments & Gear > Guitars & Basses > Other Guitars"
 },
 {
   "order": 41778,
   "name": "Musical Instruments & Gear > Instruction Books, CDs & Video > Brass"
 },
 {
   "order": 41779,
   "name": "Musical Instruments & Gear > Instruction Books, CDs & Video > Guitar"
 },
 {
   "order": 38101,
   "name": "Musical Instruments & Gear > Instruction Books, CDs & Video > Keyboard & Piano"
 },
 {
   "order": 117051,
   "name": "Musical Instruments & Gear > Instruction Books, CDs & Video > Music Theory & Ear Training"
 },
 {
   "order": 41782,
   "name": "Musical Instruments & Gear > Instruction Books, CDs & Video > Percussion"
 },
 {
   "order": 38102,
   "name": "Musical Instruments & Gear > Instruction Books, CDs & Video > Strings"
 },
 {
   "order": 159982,
   "name": "Musical Instruments & Gear > Instruction Books, CDs & Video > Voice"
 },
 {
   "order": 41788,
   "name": "Musical Instruments & Gear > Instruction Books, CDs & Video > Wind & Woodwinds"
 },
 {
   "order": 23308,
   "name": "Musical Instruments & Gear > Instruction Books, CDs & Video > Other Music Instruction"
 },
 {
   "order": 64602,
   "name": "Musical Instruments & Gear > Karaoke Entertainment > Complete Karaoke Systems"
 },
 {
   "order": 64606,
   "name": "Musical Instruments & Gear > Karaoke Entertainment > Players & Mic-Based Players"
 },
 {
   "order": 64604,
   "name": "Musical Instruments & Gear > Karaoke Entertainment > Karaoke CDGs, DVDs & Media"
 },
 {
   "order": 50590,
   "name": "Musical Instruments & Gear > Karaoke Entertainment > Karaoke Microphones"
 },
 {
   "order": 64605,
   "name": "Musical Instruments & Gear > Karaoke Entertainment > Karaoke Mixers"
 },
 {
   "order": 163828,
   "name": "Musical Instruments & Gear > Karaoke Entertainment > Other Karaoke Entertainment"
 },
 {
   "order": 41441,
   "name": "Musical Instruments & Gear > Percussion > Cymbals"
 },
 {
   "order": 38093,
   "name": "Musical Instruments & Gear > Percussion > Drums > Bass Drums"
 },
 {
   "order": 38069,
   "name": "Musical Instruments & Gear > Percussion > Drums > Electronic Drums"
 },
 {
   "order": 38095,
   "name": "Musical Instruments & Gear > Percussion > Drums > Snare Drums"
 },
 {
   "order": 38096,
   "name": "Musical Instruments & Gear > Percussion > Drums > Toms"
 },
 {
   "order": 38097,
   "name": "Musical Instruments & Gear > Percussion > Drums > Sets & Kits"
 },
 {
   "order": 10175,
   "name": "Musical Instruments & Gear > Percussion > Drums > Other Drums"
 },
 {
   "order": 93771,
   "name": "Musical Instruments & Gear > Percussion > Folk & World Drums > Bodhráns/Irish Drums"
 },
 {
   "order": 181229,
   "name": "Musical Instruments & Gear > Percussion > Folk & World Drums > Bongos"
 },
 {
   "order": 181230,
   "name": "Musical Instruments & Gear > Percussion > Folk & World Drums > Cajons"
 },
 {
   "order": 181231,
   "name": "Musical Instruments & Gear > Percussion > Folk & World Drums > Congas"
 },
 {
   "order": 181232,
   "name": "Musical Instruments & Gear > Percussion > Folk & World Drums > Darbukas"
 },
 {
   "order": 181233,
   "name": "Musical Instruments & Gear > Percussion > Folk & World Drums > Dhols"
 },
 {
   "order": 181234,
   "name": "Musical Instruments & Gear > Percussion > Folk & World Drums > Dholaks"
 },
 {
   "order": 181235,
   "name": "Musical Instruments & Gear > Percussion > Folk & World Drums > Djembes"
 },
 {
   "order": 181236,
   "name": "Musical Instruments & Gear > Percussion > Folk & World Drums > Handpans"
 },
 {
   "order": 181238,
   "name": "Musical Instruments & Gear > Percussion > Folk & World Drums > Mridangams"
 },
 {
   "order": 181239,
   "name": "Musical Instruments & Gear > Percussion > Folk & World Drums > Steel Drums"
 },
 {
   "order": 181240,
   "name": "Musical Instruments & Gear > Percussion > Folk & World Drums > Surdos"
 },
 {
   "order": 181241,
   "name": "Musical Instruments & Gear > Percussion > Folk & World Drums > Tablas"
 },
 {
   "order": 181242,
   "name": "Musical Instruments & Gear > Percussion > Folk & World Drums > Talking Drums"
 },
 {
   "order": 181243,
   "name": "Musical Instruments & Gear > Percussion > Folk & World Drums > Tamboras"
 },
 {
   "order": 181237,
   "name": "Musical Instruments & Gear > Percussion > Folk & World Drums > Udu & Ibo Drums"
 },
 {
   "order": 181245,
   "name": "Musical Instruments & Gear > Percussion > Folk & World Drums > Other Folk & World Drums"
 },
 {
   "order": 148621,
   "name": "Musical Instruments & Gear > Percussion > Hand Percussion > Jaw Harps"
 },
 {
   "order": 148620,
   "name": "Musical Instruments & Gear > Percussion > Hand Percussion > Kalimbas"
 },
 {
   "order": 47090,
   "name": "Musical Instruments & Gear > Percussion > Hand Percussion > Shakers & Small Percussion"
 },
 {
   "order": 39178,
   "name": "Musical Instruments & Gear > Percussion > Hand Percussion > Singing Bowls"
 },
 {
   "order": 41457,
   "name": "Musical Instruments & Gear > Percussion > Hand Percussion > Tambourines"
 },
 {
   "order": 181248,
   "name": "Musical Instruments & Gear > Percussion > Hand Percussion > Other Hand Percussion"
 },
 {
   "order": 41440,
   "name": "Musical Instruments & Gear > Percussion > Orchestral Percussion > Bells & Chimes"
 },
 {
   "order": 181250,
   "name": "Musical Instruments & Gear > Percussion > Orchestral Percussion > Gongs"
 },
 {
   "order": 41458,
   "name": "Musical Instruments & Gear > Percussion > Orchestral Percussion > Mallet Percussion"
 },
 {
   "order": 181251,
   "name": "Musical Instruments & Gear > Percussion > Orchestral Percussion > Timpani"
 },
 {
   "order": 181253,
   "name": "Musical Instruments & Gear > Percussion > Orchestral Percussion > Other Orchestral Percussion"
 },
 {
   "order": 41449,
   "name": "Musical Instruments & Gear > Percussion > Parts & Accessories > Bags & Cases"
 },
 {
   "order": 41450,
   "name": "Musical Instruments & Gear > Percussion > Parts & Accessories > Heads"
 },
 {
   "order": 41451,
   "name": "Musical Instruments & Gear > Percussion > Parts & Accessories > Hoops & Rims"
 },
 {
   "order": 47089,
   "name": "Musical Instruments & Gear > Percussion > Parts & Accessories > Mounts & Assembly Hardware"
 },
 {
   "order": 41452,
   "name": "Musical Instruments & Gear > Percussion > Parts & Accessories > Pedals"
 },
 {
   "order": 47579,
   "name": "Musical Instruments & Gear > Percussion > Parts & Accessories > Practice Pads"
 },
 {
   "order": 41453,
   "name": "Musical Instruments & Gear > Percussion > Parts & Accessories > Stands"
 },
 {
   "order": 41456,
   "name": "Musical Instruments & Gear > Percussion > Parts & Accessories > Sticks, Brushes, & Mallets"
 },
 {
   "order": 47084,
   "name": "Musical Instruments & Gear > Percussion > Parts & Accessories > Stools & Thrones"
 },
 {
   "order": 10173,
   "name": "Musical Instruments & Gear > Percussion > Parts & Accessories > Other Percussion Parts & Accs"
 },
 {
   "order": 622,
   "name": "Musical Instruments & Gear > Percussion > Other Percussion"
 },
 {
   "order": 38088,
   "name": "Musical Instruments & Gear > Pianos, Keyboards & Organs > Electronic Keyboards"
 },
 {
   "order": 182149,
   "name": "Musical Instruments & Gear > Pianos, Keyboards & Organs > Harpsichord"
 },
 {
   "order": 16219,
   "name": "Musical Instruments & Gear > Pianos, Keyboards & Organs > Organs"
 },
 {
   "order": 43376,
   "name": "Musical Instruments & Gear > Pianos, Keyboards & Organs > Pianos > Grand & Baby Grand Pianos"
 },
 {
   "order": 85860,
   "name": "Musical Instruments & Gear > Pianos, Keyboards & Organs > Pianos > Digital Pianos"
 },
 {
   "order": 43377,
   "name": "Musical Instruments & Gear > Pianos, Keyboards & Organs > Pianos > Upright Pianos"
 },
 {
   "order": 16220,
   "name": "Musical Instruments & Gear > Pianos, Keyboards & Organs > Pianos > Other Pianos"
 },
 {
   "order": 181269,
   "name": "Musical Instruments & Gear > Pianos, Keyboards & Organs > Folk & World > Accordions"
 },
 {
   "order": 181270,
   "name": "Musical Instruments & Gear > Pianos, Keyboards & Organs > Folk & World > Concertinas"
 },
 {
   "order": 181274,
   "name": "Musical Instruments & Gear > Pianos, Keyboards & Organs > Folk & World > Harmoniums"
 },
 {
   "order": 181490,
   "name": "Musical Instruments & Gear > Pianos, Keyboards & Organs > Folk & World > Other Folk & World"
 },
 {
   "order": 182147,
   "name": "Musical Instruments & Gear > Pianos, Keyboards & Organs > Parts & Accessories > Accordion Accessories"
 },
 {
   "order": 148727,
   "name": "Musical Instruments & Gear > Pianos, Keyboards & Organs > Parts & Accessories > Cases & Bags"
 },
 {
   "order": 148725,
   "name": "Musical Instruments & Gear > Pianos, Keyboards & Organs > Parts & Accessories > Keyboard Covers"
 },
 {
   "order": 148728,
   "name": "Musical Instruments & Gear > Pianos, Keyboards & Organs > Parts & Accessories > Pedals"
 },
 {
   "order": 148726,
   "name": "Musical Instruments & Gear > Pianos, Keyboards & Organs > Parts & Accessories > Piano Lamps"
 },
 {
   "order": 182148,
   "name": "Musical Instruments & Gear > Pianos, Keyboards & Organs > Parts & Accessories > Repair & Maintenance"
 },
 {
   "order": 47042,
   "name": "Musical Instruments & Gear > Pianos, Keyboards & Organs > Parts & Accessories > Stands"
 },
 {
   "order": 117049,
   "name": "Musical Instruments & Gear > Pianos, Keyboards & Organs > Parts & Accessories > Stools & Benches"
 },
 {
   "order": 21766,
   "name": "Musical Instruments & Gear > Pianos, Keyboards & Organs > Parts & Accessories > Other Parts & Accessories"
 },
 {
   "order": 1289,
   "name": "Musical Instruments & Gear > Pianos, Keyboards & Organs > Other Pianos & Keyboards"
 },
 {
   "order": 168129,
   "name": "Musical Instruments & Gear > Pro Audio Equipment > Acoustical Treatments"
 },
 {
   "order": 163896,
   "name": "Musical Instruments & Gear > Pro Audio Equipment > Amplifiers"
 },
 {
   "order": 159955,
   "name": "Musical Instruments & Gear > Pro Audio Equipment > Audio Power Conditioners"
 },
 {
   "order": 123445,
   "name": "Musical Instruments & Gear > Pro Audio Equipment > Audio/MIDI Interfaces"
 },
 {
   "order": 41459,
   "name": "Musical Instruments & Gear > Pro Audio Equipment > Cables, Snakes & Interconnects"
 },
 {
   "order": 23789,
   "name": "Musical Instruments & Gear > Pro Audio Equipment > Cases, Racks & Bags"
 },
 {
   "order": 4785,
   "name": "Musical Instruments & Gear > Pro Audio Equipment > Live & Studio Mixers"
 },
 {
   "order": 29946,
   "name": "Musical Instruments & Gear > Pro Audio Equipment > Microphones & Wireless Systems"
 },
 {
   "order": 178896,
   "name": "Musical Instruments & Gear > Pro Audio Equipment > MIDI Keyboards & Controllers"
 },
 {
   "order": 119018,
   "name": "Musical Instruments & Gear > Pro Audio Equipment > Preamps & Channel Strips"
 },
 {
   "order": 15199,
   "name": "Musical Instruments & Gear > Pro Audio Equipment > Recorders"
 },
 {
   "order": 38070,
   "name": "Musical Instruments & Gear > Pro Audio Equipment > Samplers & Sequencers"
 },
 {
   "order": 23791,
   "name": "Musical Instruments & Gear > Pro Audio Equipment > Signal Processors/Rack Effects"
 },
 {
   "order": 177027,
   "name": "Musical Instruments & Gear > Pro Audio Equipment > Software, Loops & Samples"
 },
 {
   "order": 47092,
   "name": "Musical Instruments & Gear > Pro Audio Equipment > Speaker Drivers & Horns"
 },
 {
   "order": 47091,
   "name": "Musical Instruments & Gear > Pro Audio Equipment > Speakers & Monitors"
 },
 {
   "order": 29948,
   "name": "Musical Instruments & Gear > Pro Audio Equipment > Stands, Mounts & Holders"
 },
 {
   "order": 177028,
   "name": "Musical Instruments & Gear > Pro Audio Equipment > Studio/Live Equipment Packages"
 },
 {
   "order": 38071,
   "name": "Musical Instruments & Gear > Pro Audio Equipment > Synthesizers"
 },
 {
   "order": 113484,
   "name": "Musical Instruments & Gear > Pro Audio Equipment > Parts & Accessories"
 },
 {
   "order": 119019,
   "name": "Musical Instruments & Gear > Pro Audio Equipment > Vintage Pro Audio Equipment"
 },
 {
   "order": 3278,
   "name": "Musical Instruments & Gear > Pro Audio Equipment > Other Pro Audio Equipment"
 },
 {
   "order": 182151,
   "name": "Musical Instruments & Gear > Sheet Music & Song Books > Contemporary"
 },
 {
   "order": 182152,
   "name": "Musical Instruments & Gear > Sheet Music & Song Books > Vintage & Antique"
 },
 {
   "order": 177022,
   "name": "Musical Instruments & Gear > Stage Lighting & Effects > Stage Lighting: Single Units"
 },
 {
   "order": 12921,
   "name": "Musical Instruments & Gear > Stage Lighting & Effects > Stage Lighting: Systems & Kits"
 },
 {
   "order": 177023,
   "name": "Musical Instruments & Gear > Stage Lighting & Effects > DJ Lighting: Single Units"
 },
 {
   "order": 177024,
   "name": "Musical Instruments & Gear > Stage Lighting & Effects > DJ Lighting: Systems & Kits"
 },
 {
   "order": 69960,
   "name": "Musical Instruments & Gear > Stage Lighting & Effects > Atmospheric Effects Machines"
 },
 {
   "order": 132998,
   "name": "Musical Instruments & Gear > Stage Lighting & Effects > Atmospheric Effects Fluids"
 },
 {
   "order": 182104,
   "name": "Musical Instruments & Gear > Stage Lighting & Effects > Clamps & Mounts"
 },
 {
   "order": 170088,
   "name": "Musical Instruments & Gear > Stage Lighting & Effects > Cables & Interconnects"
 },
 {
   "order": 30889,
   "name": "Musical Instruments & Gear > Stage Lighting & Effects > Stage Lighting Controllers"
 },
 {
   "order": 182103,
   "name": "Musical Instruments & Gear > Stage Lighting & Effects > Stage Lighting Dimmers"
 },
 {
   "order": 177025,
   "name": "Musical Instruments & Gear > Stage Lighting & Effects > Folding Screens & Backdrops"
 },
 {
   "order": 81967,
   "name": "Musical Instruments & Gear > Stage Lighting & Effects > Gobos, Gels, Filters & Lenses"
 },
 {
   "order": 29945,
   "name": "Musical Instruments & Gear > Stage Lighting & Effects > Lighting Stands & Trusses"
 },
 {
   "order": 81970,
   "name": "Musical Instruments & Gear > Stage Lighting & Effects > Replacement Bulbs & Lamps"
 },
 {
   "order": 12930,
   "name": "Musical Instruments & Gear > Stage Lighting & Effects > Parts & Accessories"
 },
 {
   "order": 170089,
   "name": "Musical Instruments & Gear > Stage Lighting & Effects > Other Stage Lighting & Effects"
 },
 {
   "order": 16222,
   "name": "Musical Instruments & Gear > String > Orchestral > Upright Basses"
 },
 {
   "order": 10178,
   "name": "Musical Instruments & Gear > String > Orchestral > Cellos"
 },
 {
   "order": 16225,
   "name": "Musical Instruments & Gear > String > Orchestral > Violas"
 },
 {
   "order": 38107,
   "name": "Musical Instruments & Gear > String > Orchestral > Violins"
 },
 {
   "order": 16221,
   "name": "Musical Instruments & Gear > String > Folk & World > Autoharps & Zithers"
 },
 {
   "order": 181283,
   "name": "Musical Instruments & Gear > String > Folk & World > Balalaikas"
 },
 {
   "order": 10177,
   "name": "Musical Instruments & Gear > String > Folk & World > Banjos"
 },
 {
   "order": 101567,
   "name": "Musical Instruments & Gear > String > Folk & World > Bouzoukis/Mandolas"
 },
 {
   "order": 181284,
   "name": "Musical Instruments & Gear > String > Folk & World > Erhus"
 },
 {
   "order": 181285,
   "name": "Musical Instruments & Gear > String > Folk & World > Guzhengs"
 },
 {
   "order": 16223,
   "name": "Musical Instruments & Gear > String > Folk & World > Harps & Dulcimers"
 },
 {
   "order": 112676,
   "name": "Musical Instruments & Gear > String > Folk & World > Lutes"
 },
 {
   "order": 10179,
   "name": "Musical Instruments & Gear > String > Folk & World > Mandolins"
 },
 {
   "order": 181286,
   "name": "Musical Instruments & Gear > String > Folk & World > Ouds"
 },
 {
   "order": 181287,
   "name": "Musical Instruments & Gear > String > Folk & World > Pipas"
 },
 {
   "order": 181288,
   "name": "Musical Instruments & Gear > String > Folk & World > Rebabs"
 },
 {
   "order": 181289,
   "name": "Musical Instruments & Gear > String > Folk & World > Sarods"
 },
 {
   "order": 181290,
   "name": "Musical Instruments & Gear > String > Folk & World > Sazs"
 },
 {
   "order": 112677,
   "name": "Musical Instruments & Gear > String > Folk & World > Sitars"
 },
 {
   "order": 181291,
   "name": "Musical Instruments & Gear > String > Folk & World > Setars"
 },
 {
   "order": 16224,
   "name": "Musical Instruments & Gear > String > Folk & World > Ukuleles"
 },
 {
   "order": 182163,
   "name": "Musical Instruments & Gear > String > Parts & Accessories > Bags & Cases"
 },
 {
   "order": 182164,
   "name": "Musical Instruments & Gear > String > Parts & Accessories > Bows"
 },
 {
   "order": 182165,
   "name": "Musical Instruments & Gear > String > Parts & Accessories > Bridges & Tailpieces"
 },
 {
   "order": 182166,
   "name": "Musical Instruments & Gear > String > Parts & Accessories > Care & Cleaning"
 },
 {
   "order": 182167,
   "name": "Musical Instruments & Gear > String > Parts & Accessories > Mutes"
 },
 {
   "order": 182168,
   "name": "Musical Instruments & Gear > String > Parts & Accessories > Pegs"
 },
 {
   "order": 182169,
   "name": "Musical Instruments & Gear > String > Parts & Accessories > Picks"
 },
 {
   "order": 182170,
   "name": "Musical Instruments & Gear > String > Parts & Accessories > Rests & Pads"
 },
 {
   "order": 182171,
   "name": "Musical Instruments & Gear > String > Parts & Accessories > Stands"
 },
 {
   "order": 182172,
   "name": "Musical Instruments & Gear > String > Parts & Accessories > Strings"
 },
 {
   "order": 182173,
   "name": "Musical Instruments & Gear > String > Parts & Accessories > Other Accessories"
 },
 {
   "order": 623,
   "name": "Musical Instruments & Gear > String > Other String Instruments"
 },
 {
   "order": 16227,
   "name": "Musical Instruments & Gear > Wind & Woodwind > Band & Orchestral > Bassoons"
 },
 {
   "order": 47096,
   "name": "Musical Instruments & Gear > Wind & Woodwind > Band & Orchestral > Clarinets"
 },
 {
   "order": 10183,
   "name": "Musical Instruments & Gear > Wind & Woodwind > Band & Orchestral > Flutes"
 },
 {
   "order": 112678,
   "name": "Musical Instruments & Gear > Wind & Woodwind > Band & Orchestral > Oboes"
 },
 {
   "order": 16229,
   "name": "Musical Instruments & Gear > Wind & Woodwind > Band & Orchestral > Piccolos"
 },
 {
   "order": 16230,
   "name": "Musical Instruments & Gear > Wind & Woodwind > Band & Orchestral > Recorders"
 },
 {
   "order": 16231,
   "name": "Musical Instruments & Gear > Wind & Woodwind > Band & Orchestral > Saxophones"
 },
 {
   "order": 16226,
   "name": "Musical Instruments & Gear > Wind & Woodwind > Folk & World > Bagpipes"
 },
 {
   "order": 90849,
   "name": "Musical Instruments & Gear > Wind & Woodwind > Folk & World > Didgeridoos"
 },
 {
   "order": 181271,
   "name": "Musical Instruments & Gear > Wind & Woodwind > Folk & World > Dizis"
 },
 {
   "order": 181272,
   "name": "Musical Instruments & Gear > Wind & Woodwind > Folk & World > Duduks"
 },
 {
   "order": 181273,
   "name": "Musical Instruments & Gear > Wind & Woodwind > Folk & World > Guanzis"
 },
 {
   "order": 47078,
   "name": "Musical Instruments & Gear > Wind & Woodwind > Folk & World > Harmonicas"
 },
 {
   "order": 181275,
   "name": "Musical Instruments & Gear > Wind & Woodwind > Folk & World > Hulusis"
 },
 {
   "order": 181276,
   "name": "Musical Instruments & Gear > Wind & Woodwind > Folk & World > Kavals"
 },
 {
   "order": 178976,
   "name": "Musical Instruments & Gear > Wind & Woodwind > Folk & World > Melodicas"
 },
 {
   "order": 181277,
   "name": "Musical Instruments & Gear > Wind & Woodwind > Folk & World > Neys"
 },
 {
   "order": 180017,
   "name": "Musical Instruments & Gear > Wind & Woodwind > Folk & World > Ocarinas"
 },
 {
   "order": 181278,
   "name": "Musical Instruments & Gear > Wind & Woodwind > Folk & World > Panflutes"
 },
 {
   "order": 181279,
   "name": "Musical Instruments & Gear > Wind & Woodwind > Folk & World > Shakuhachis"
 },
 {
   "order": 91502,
   "name": "Musical Instruments & Gear > Wind & Woodwind > Folk & World > Whistles"
 },
 {
   "order": 182154,
   "name": "Musical Instruments & Gear > Wind & Woodwind > Parts & Accessories > Bags & Cases"
 },
 {
   "order": 182155,
   "name": "Musical Instruments & Gear > Wind & Woodwind > Parts & Accessories > Care & Cleaning"
 },
 {
   "order": 182156,
   "name": "Musical Instruments & Gear > Wind & Woodwind > Parts & Accessories > Ligatures & Caps"
 },
 {
   "order": 182157,
   "name": "Musical Instruments & Gear > Wind & Woodwind > Parts & Accessories > Mouthpieces"
 },
 {
   "order": 182158,
   "name": "Musical Instruments & Gear > Wind & Woodwind > Parts & Accessories > Reeds"
 },
 {
   "order": 182159,
   "name": "Musical Instruments & Gear > Wind & Woodwind > Parts & Accessories > Stands"
 },
 {
   "order": 182160,
   "name": "Musical Instruments & Gear > Wind & Woodwind > Parts & Accessories > Straps"
 },
 {
   "order": 182161,
   "name": "Musical Instruments & Gear > Wind & Woodwind > Parts & Accessories > Other Accessories"
 },
 {
   "order": 624,
   "name": "Musical Instruments & Gear > Wind & Woodwind > Other Wind & Woodwind"
 },
 {
   "order": 106454,
   "name": "Musical Instruments & Gear > Equipment > Clothing & Uniforms"
 },
 {
   "order": 39179,
   "name": "Musical Instruments & Gear > Equipment > Hearing Protection"
 },
 {
   "order": 41404,
   "name": "Musical Instruments & Gear > Equipment > Metronomes"
 },
 {
   "order": 101555,
   "name": "Musical Instruments & Gear > Equipment > Music Stands"
 },
 {
   "order": 64388,
   "name": "Musical Instruments & Gear > Equipment > Tuners"
 },
 {
   "order": 1288,
   "name": "Musical Instruments & Gear > Equipment > Other Musical Instrument Equip"
 },
 {
   "order": 181158,
   "name": "Musical Instruments & Gear > Vintage Musical Instruments > Vintage Brass > Baritones"
 },
 {
   "order": 181159,
   "name": "Musical Instruments & Gear > Vintage Musical Instruments > Vintage Brass > Bugles"
 },
 {
   "order": 159946,
   "name": "Musical Instruments & Gear > Vintage Musical Instruments > Vintage Brass > Cornets"
 },
 {
   "order": 181156,
   "name": "Musical Instruments & Gear > Vintage Musical Instruments > Vintage Brass > Mellophones"
 },
 {
   "order": 181157,
   "name": "Musical Instruments & Gear > Vintage Musical Instruments > Vintage Brass > Sousaphones"
 },
 {
   "order": 118976,
   "name": "Musical Instruments & Gear > Vintage Musical Instruments > Vintage Brass > Trombones"
 },
 {
   "order": 118975,
   "name": "Musical Instruments & Gear > Vintage Musical Instruments > Vintage Brass > Trumpets"
 },
 {
   "order": 181160,
   "name": "Musical Instruments & Gear > Vintage Musical Instruments > Vintage Brass > Tubas"
 },
 {
   "order": 181161,
   "name": "Musical Instruments & Gear > Vintage Musical Instruments > Vintage Brass > Parts & Accessories"
 },
 {
   "order": 118977,
   "name": "Musical Instruments & Gear > Vintage Musical Instruments > Vintage Brass > Other Vintage Brass"
 },
 {
   "order": 118979,
   "name": "Musical Instruments & Gear > Vintage Musical Instruments > Vintage Guitars & Basses > Acoustic Guitars"
 },
 {
   "order": 118984,
   "name": "Musical Instruments & Gear > Vintage Musical Instruments > Vintage Guitars & Basses > Bass Guitars"
 },
 {
   "order": 181164,
   "name": "Musical Instruments & Gear > Vintage Musical Instruments > Vintage Guitars & Basses > Classical Guitars"
 },
 {
   "order": 181167,
   "name": "Musical Instruments & Gear > Vintage Musical Instruments > Vintage Guitars & Basses > Cigar Box Guitars"
 },
 {
   "order": 118985,
   "name": "Musical Instruments & Gear > Vintage Musical Instruments > Vintage Guitars & Basses > Electric Guitars"
 },
 {
   "order": 118983,
   "name": "Musical Instruments & Gear > Vintage Musical Instruments > Vintage Guitars & Basses > Guitar Amplifiers"
 },
 {
   "order": 181166,
   "name": "Musical Instruments & Gear > Vintage Musical Instruments > Vintage Guitars & Basses > Lap & Steel Guitars"
 },
 {
   "order": 181165,
   "name": "Musical Instruments & Gear > Vintage Musical Instruments > Vintage Guitars & Basses > Resonator"
 },
 {
   "order": 181168,
   "name": "Musical Instruments & Gear > Vintage Musical Instruments > Vintage Guitars & Basses > Parts"
 },
 {
   "order": 181169,
   "name": "Musical Instruments & Gear > Vintage Musical Instruments > Vintage Guitars & Basses > Accessories"
 },
 {
   "order": 118994,
   "name": "Musical Instruments & Gear > Vintage Musical Instruments > Vintage Guitars & Basses > Other Vintage Guitars"
 },
 {
   "order": 181171,
   "name": "Musical Instruments & Gear > Vintage Musical Instruments > Vintage Percussion > Cymbals"
 },
 {
   "order": 181173,
   "name": "Musical Instruments & Gear > Vintage Musical Instruments > Vintage Percussion > Drums > Bass"
 },
 {
   "order": 181174,
   "name": "Musical Instruments & Gear > Vintage Musical Instruments > Vintage Percussion > Drums > Electronic Drums"
 },
 {
   "order": 181175,
   "name": "Musical Instruments & Gear > Vintage Musical Instruments > Vintage Percussion > Drums > Snare Drums"
 },
 {
   "order": 181176,
   "name": "Musical Instruments & Gear > Vintage Musical Instruments > Vintage Percussion > Drums > Toms"
 },
 {
   "order": 181177,
   "name": "Musical Instruments & Gear > Vintage Musical Instruments > Vintage Percussion > Drums > Sets & Kits"
 },
 {
   "order": 181179,
   "name": "Musical Instruments & Gear > Vintage Musical Instruments > Vintage Percussion > Folk & World Drums"
 },
 {
   "order": 181185,
   "name": "Musical Instruments & Gear > Vintage Musical Instruments > Vintage Percussion > Hand Percussion > Jaw Harps"
 },
 {
   "order": 181183,
   "name": "Musical Instruments & Gear > Vintage Musical Instruments > Vintage Percussion > Hand Percussion > Kalimbas"
 },
 {
   "order": 181181,
   "name": "Musical Instruments & Gear > Vintage Musical Instruments > Vintage Percussion > Hand Percussion > Shakers & Small Percussion"
 },
 {
   "order": 181184,
   "name": "Musical Instruments & Gear > Vintage Musical Instruments > Vintage Percussion > Hand Percussion > Singing Bowls"
 },
 {
   "order": 181182,
   "name": "Musical Instruments & Gear > Vintage Musical Instruments > Vintage Percussion > Hand Percussion > Tambourines"
 },
 {
   "order": 181189,
   "name": "Musical Instruments & Gear > Vintage Musical Instruments > Vintage Percussion > Orchestral Percussion > Gongs"
 },
 {
   "order": 181190,
   "name": "Musical Instruments & Gear > Vintage Musical Instruments > Vintage Percussion > Orchestral Percussion > Bells & Chimes"
 },
 {
   "order": 181188,
   "name": "Musical Instruments & Gear > Vintage Musical Instruments > Vintage Percussion > Orchestral Percussion > Mallet Percussion"
 },
 {
   "order": 182214,
   "name": "Musical Instruments & Gear > Vintage Musical Instruments > Vintage Percussion > Parts & Accessories"
 },
 {
   "order": 181192,
   "name": "Musical Instruments & Gear > Vintage Musical Instruments > Vintage Percussion > Other Vintage Percussion"
 },
 {
   "order": 181194,
   "name": "Musical Instruments & Gear > Vintage Musical Instruments > Vintage Pianos & Keyboards > Electronic Keyboards"
 },
 {
   "order": 181195,
   "name": "Musical Instruments & Gear > Vintage Musical Instruments > Vintage Pianos & Keyboards > Organs"
 },
 {
   "order": 181197,
   "name": "Musical Instruments & Gear > Vintage Musical Instruments > Vintage Pianos & Keyboards > Pianos > Grand & Baby Grand Pianos"
 },
 {
   "order": 181198,
   "name": "Musical Instruments & Gear > Vintage Musical Instruments > Vintage Pianos & Keyboards > Pianos > Upright Pianos"
 },
 {
   "order": 181199,
   "name": "Musical Instruments & Gear > Vintage Musical Instruments > Vintage Pianos & Keyboards > Pianos > Digital Pianos"
 },
 {
   "order": 159954,
   "name": "Musical Instruments & Gear > Vintage Musical Instruments > Vintage Pianos & Keyboards > Pianos > Player Pianos"
 },
 {
   "order": 178895,
   "name": "Musical Instruments & Gear > Vintage Musical Instruments > Vintage Pianos & Keyboards > Pianos > Player Piano Rolls"
 },
 {
   "order": 181211,
   "name": "Musical Instruments & Gear > Vintage Musical Instruments > Vintage Pianos & Keyboards > Folk & World > Accordions"
 },
 {
   "order": 181213,
   "name": "Musical Instruments & Gear > Vintage Musical Instruments > Vintage Pianos & Keyboards > Folk & World > Concertinas"
 },
 {
   "order": 182215,
   "name": "Musical Instruments & Gear > Vintage Musical Instruments > Vintage Pianos & Keyboards > Parts & Accessories"
 },
 {
   "order": 181201,
   "name": "Musical Instruments & Gear > Vintage Musical Instruments > Vintage Pianos & Keyboards > Other Vintage Pianos"
 },
 {
   "order": 181257,
   "name": "Musical Instruments & Gear > Vintage Musical Instruments > Vintage String > Orchestral > Cellos"
 },
 {
   "order": 181256,
   "name": "Musical Instruments & Gear > Vintage Musical Instruments > Vintage String > Orchestral > Upright Basses"
 },
 {
   "order": 181258,
   "name": "Musical Instruments & Gear > Vintage Musical Instruments > Vintage String > Orchestral > Violas"
 },
 {
   "order": 119026,
   "name": "Musical Instruments & Gear > Vintage Musical Instruments > Vintage String > Orchestral > Violins"
 },
 {
   "order": 181261,
   "name": "Musical Instruments & Gear > Vintage Musical Instruments > Vintage String > Folk & World > Autoharps & Zithers"
 },
 {
   "order": 181262,
   "name": "Musical Instruments & Gear > Vintage Musical Instruments > Vintage String > Folk & World > Balalaikas"
 },
 {
   "order": 119024,
   "name": "Musical Instruments & Gear > Vintage Musical Instruments > Vintage String > Folk & World > Banjos"
 },
 {
   "order": 181263,
   "name": "Musical Instruments & Gear > Vintage Musical Instruments > Vintage String > Folk & World > Harps & Dulcimers"
 },
 {
   "order": 181264,
   "name": "Musical Instruments & Gear > Vintage Musical Instruments > Vintage String > Folk & World > Lutes"
 },
 {
   "order": 181265,
   "name": "Musical Instruments & Gear > Vintage Musical Instruments > Vintage String > Folk & World > Mandolins"
 },
 {
   "order": 119025,
   "name": "Musical Instruments & Gear > Vintage Musical Instruments > Vintage String > Folk & World > Ukuleles"
 },
 {
   "order": 182217,
   "name": "Musical Instruments & Gear > Vintage Musical Instruments > Vintage String > Parts & Accessories"
 },
 {
   "order": 119027,
   "name": "Musical Instruments & Gear > Vintage Musical Instruments > Vintage String > Other Vintage String"
 },
 {
   "order": 181204,
   "name": "Musical Instruments & Gear > Vintage Musical Instruments > Vintage Wind & Woodwind > Band & Orchestral > Bassoons"
 },
 {
   "order": 119029,
   "name": "Musical Instruments & Gear > Vintage Musical Instruments > Vintage Wind & Woodwind > Band & Orchestral > Clarinets"
 },
 {
   "order": 181205,
   "name": "Musical Instruments & Gear > Vintage Musical Instruments > Vintage Wind & Woodwind > Band & Orchestral > Flutes"
 },
 {
   "order": 181206,
   "name": "Musical Instruments & Gear > Vintage Musical Instruments > Vintage Wind & Woodwind > Band & Orchestral > Oboes"
 },
 {
   "order": 181207,
   "name": "Musical Instruments & Gear > Vintage Musical Instruments > Vintage Wind & Woodwind > Band & Orchestral > Piccolos"
 },
 {
   "order": 181208,
   "name": "Musical Instruments & Gear > Vintage Musical Instruments > Vintage Wind & Woodwind > Band & Orchestral > Recorders"
 },
 {
   "order": 119030,
   "name": "Musical Instruments & Gear > Vintage Musical Instruments > Vintage Wind & Woodwind > Band & Orchestral > Saxophones"
 },
 {
   "order": 181212,
   "name": "Musical Instruments & Gear > Vintage Musical Instruments > Vintage Wind & Woodwind > Folk & World > Bagpipes"
 },
 {
   "order": 119095,
   "name": "Musical Instruments & Gear > Vintage Musical Instruments > Vintage Wind & Woodwind > Folk & World > Harmonicas"
 },
 {
   "order": 181214,
   "name": "Musical Instruments & Gear > Vintage Musical Instruments > Vintage Wind & Woodwind > Folk & World > Melodicas"
 },
 {
   "order": 181215,
   "name": "Musical Instruments & Gear > Vintage Musical Instruments > Vintage Wind & Woodwind > Folk & World > Ocarinas"
 },
 {
   "order": 181216,
   "name": "Musical Instruments & Gear > Vintage Musical Instruments > Vintage Wind & Woodwind > Folk & World > Whistles"
 },
 {
   "order": 182216,
   "name": "Musical Instruments & Gear > Vintage Musical Instruments > Vintage Wind & Woodwind > Parts & Accessories"
 },
 {
   "order": 181218,
   "name": "Musical Instruments & Gear > Vintage Musical Instruments > Vintage Wind & Woodwind > Other Vintage Woodwind"
 },
 {
   "order": 52555,
   "name": "Musical Instruments & Gear > Wholesale Lots"
 }
 
]
    }
  ],
  "listings":[
  ]
}